{
  "users": [
    { "display_name": "Person A" },
    { "display_name": "Person B" }
  ],
  "accounts": [
    { "owner_name": "Person A", "institution": "Amex", "account_name": "Cobalt", "account_type": "credit_card" },
    { "owner_name": "Person A", "institution": "Wealthsimple", "account_name": "Visa", "account_type": "credit_card" },
    { "owner_name": "Person A", "institution": "Wealthsimple", "account_name": "Chequing", "account_type": "chequing" }
  ],
  "import_files": [
    { "filename": "my-amex-statement.csv", "account_key": "Amex:Cobalt", "source_format": "amex_monthly", "statement_total": 1234.56 },
    { "filename": "my-visa-export.csv", "account_key": "Wealthsimple:Visa", "source_format": "ws_visa" }
  ],
  "merchant_rules": [
    ["NETFLIX", "Subscriptions"],
    ["COSTCO", "Groceries"],
    ["UBER TRIP", "Transport"]
  ],
  "user_corrections": [
    ["LOCAL DELI", "Eating Out"]
  ]
}
